large_image_source_rasterio/__init__.py
large_image_source_rasterio/girder_source.py
large_image_source_rasterio-1.34.0.dist-info/licenses/LICENSE
large_image_source_rasterio-1.34.0.dist-info/METADATA
large_image_source_rasterio-1.34.0.dist-info/WHEEL
large_image_source_rasterio-1.34.0.dist-info/entry_points.txt
large_image_source_rasterio-1.34.0.dist-info/top_level.txt
large_image_source_rasterio-1.34.0.dist-info/RECORD
